neurlink/__init__.py
neurlink/models/__init__.py
neurlink/models/hrnet.py
neurlink/models/resnet.py
neurlink/models/resnet_bak.py
neurlink/nerves/__init__.py
neurlink/nerves/common_types.py
neurlink/nerves/conv.py
neurlink/nerves/misc.py
neurlink/nerves/nerve.py
neurlink/nerves/pool.py
neurlink/nerves/utils.py
neurlink/nn/__init__.py
neurlink/nn/functional/__init__.py
neurlink/nn/functional/regularization.py
neurlink/nn/modules/__init__.py
neurlink/nn/modules/regularization.py
neurlink-0.2.2.dist-info/LICENCE
neurlink-0.2.2.dist-info/METADATA
neurlink-0.2.2.dist-info/WHEEL
neurlink-0.2.2.dist-info/top_level.txt
neurlink-0.2.2.dist-info/RECORD
