Metadata-Version: 2.1
Name: neurlink
Version: 0.2.2
Summary: a compact neuron network model definition grammar
Home-page: https://github.com/tjyuyao/neurlink
Author: Yuyao Huang
Author-email: huangyuyao@outlook.com
License: UNKNOWN
Project-URL: Bug Tracker, https://github.com/tjyuyao/neurlink/issues
Platform: UNKNOWN
Classifier: Programming Language :: Python :: 3
Classifier: License :: OSI Approved :: MIT License
Classifier: Operating System :: OS Independent
Requires-Python: >=3.6
License-File: LICENCE
Requires-Dist: einops (>=0.4.1)
